{
  "blocks": [
    {
      "round_number": 0,
      "contributions": [],
      "previous_hash": "0",
      "timestamp": 1784286697.7327015,
      "hash": "bbb5f0f7a1fb75db2e49916161297a0cee18f7004c5093f7df95625c9cff52fb"
    },
    {
      "round_number": 1,
      "contributions": [
        {
          "client_id": 2,
          "weights_hash": "c8f68608e83806568a1097a78daca594cfbfa9449b1efecde72640e63ed8ab7f",
          "num_samples": 20000,
          "l2_deviation": 0.4834,
          "is_suspect": false
        },
        {
          "client_id": 0,
          "weights_hash": "7bd81fbd9c21c5017405ded64f43f2c03c0dbed133350473ded0a305339e6a3c",
          "num_samples": 20000,
          "l2_deviation": 0.5256,
          "is_suspect": true
        },
        {
          "client_id": 1,
          "weights_hash": "9ef109190cc0722452ba8f9e363b14e420f6aaade8b1710a454125f1e74b8fbd",
          "num_samples": 20000,
          "l2_deviation": 0.4737,
          "is_suspect": false
        }
      ],
      "previous_hash": "bbb5f0f7a1fb75db2e49916161297a0cee18f7004c5093f7df95625c9cff52fb",
      "timestamp": 1784286825.4725842,
      "hash": "7be6e74f523e60a13a29b4278ca09ef4f218239ba19473bb4e079b126ff2cbe9"
    },
    {
      "round_number": 2,
      "contributions": [
        {
          "client_id": 1,
          "weights_hash": "c9292bb808c59886f1ec7fcff7ac75654be98264e6dc0214e020878ea1dc5c74",
          "num_samples": 20000,
          "l2_deviation": Infinity,
          "is_suspect": true
        },
        {
          "client_id": 0,
          "weights_hash": "da5e247abb5003a950b2bde8ec5773a7c8122bdda68135b848b12c11e8632371",
          "num_samples": 20000,
          "l2_deviation": Infinity,
          "is_suspect": false
        },
        {
          "client_id": 2,
          "weights_hash": "eb120d5ee40498401455a4ab44438db841d83a7cb489f8906b192d8d3c3cc1b8",
          "num_samples": 20000,
          "l2_deviation": Infinity,
          "is_suspect": false
        }
      ],
      "previous_hash": "7be6e74f523e60a13a29b4278ca09ef4f218239ba19473bb4e079b126ff2cbe9",
      "timestamp": 1784286946.2651346,
      "hash": "60d85361869708029e7dcf1833ad8cc4dcee81609e1fafd070b244c211aa4624"
    },
    {
      "round_number": 3,
      "contributions": [
        {
          "client_id": 2,
          "weights_hash": "0a821af93e085c4c3e382013db96a6f0cdd82067134efe3427d503ce1e8fe3eb",
          "num_samples": 20000,
          "l2_deviation": 765600296.8802,
          "is_suspect": false
        },
        {
          "client_id": 0,
          "weights_hash": "ac0a2da4a40694913ccd05faacaa3c3c0aad0a9f618b37d7d3949566dffa08e9",
          "num_samples": 20000,
          "l2_deviation": 1584874436.3933,
          "is_suspect": true
        },
        {
          "client_id": 1,
          "weights_hash": "88f23ff712018df2f0351e8797d890a0c8df1c0147f713ab9b12e7043e1b5bea",
          "num_samples": 20000,
          "l2_deviation": 875743958.867,
          "is_suspect": false
        }
      ],
      "previous_hash": "60d85361869708029e7dcf1833ad8cc4dcee81609e1fafd070b244c211aa4624",
      "timestamp": 1784287067.492751,
      "hash": "456f2aeb87d6b8d9149d2c0d378480a24810c94f31b335c4299b4e839c76682b"
    },
    {
      "round_number": 4,
      "contributions": [
        {
          "client_id": 1,
          "weights_hash": "045b4c9bf3f608719cf97367c16bafdbcce5b10dc308011a45a9e171886ce738",
          "num_samples": 20000,
          "l2_deviation": 14798148.396,
          "is_suspect": false
        },
        {
          "client_id": 0,
          "weights_hash": "d84ccecac4bf0175c87bc49c2cb60ff4fdcbd3bf89eeb8e5930d29c6c6002d29",
          "num_samples": 20000,
          "l2_deviation": 14906905.8553,
          "is_suspect": false
        },
        {
          "client_id": 2,
          "weights_hash": "d44325f0150497b9ebca42e7adc66e596e90a9ca23e062821c8f6980f1d757ea",
          "num_samples": 20000,
          "l2_deviation": 26250806.0727,
          "is_suspect": true
        }
      ],
      "previous_hash": "456f2aeb87d6b8d9149d2c0d378480a24810c94f31b335c4299b4e839c76682b",
      "timestamp": 1784287188.035034,
      "hash": "e5db30ce7049ba08ef5e98ddc1c2ca026da7b51f27fffc15e3f2af57db9010f3"
    },
    {
      "round_number": 5,
      "contributions": [
        {
          "client_id": 0,
          "weights_hash": "82951fd491ce9ad276491cf325a55ecb3c75affe74974dc71224284d14506fc2",
          "num_samples": 20000,
          "l2_deviation": 1288378.7881,
          "is_suspect": false
        },
        {
          "client_id": 2,
          "weights_hash": "f334487aab171135fb8788755a0787e80e763290b0bb755f7c5fc3fb5eb33f06",
          "num_samples": 20000,
          "l2_deviation": 3688092.9442,
          "is_suspect": false
        },
        {
          "client_id": 1,
          "weights_hash": "c07f01393e21a7a26bdd6240a84de417f9bcf362df8b2cab8c69bdc8c953c989",
          "num_samples": 20000,
          "l2_deviation": 3884646.3336,
          "is_suspect": true
        }
      ],
      "previous_hash": "e5db30ce7049ba08ef5e98ddc1c2ca026da7b51f27fffc15e3f2af57db9010f3",
      "timestamp": 1784287308.8769667,
      "hash": "d3351bca59b273da8bbc8fef7abb88152b857c728e45f182edcb60e6c6d530e7"
    }
  ],
  "metrics": [
    {
      "round": 1,
      "overhead_seconds": 0.0212,
      "num_clients": 3
    },
    {
      "round": 2,
      "overhead_seconds": 0.0195,
      "num_clients": 3
    },
    {
      "round": 3,
      "overhead_seconds": 0.0196,
      "num_clients": 3
    },
    {
      "round": 4,
      "overhead_seconds": 0.0196,
      "num_clients": 3
    },
    {
      "round": 5,
      "overhead_seconds": 0.0204,
      "num_clients": 3
    }
  ]
}